machine_learning_tools/__init__.py
machine_learning_tools/clustering_ml.py
machine_learning_tools/data_annotation_utils.py
machine_learning_tools/data_input_utils.py
machine_learning_tools/dimensionality_reduction_ml.py
machine_learning_tools/dimensionality_reduction_utils.py
machine_learning_tools/evaluation_metrics_utils.py
machine_learning_tools/feature_selection_utils.py
machine_learning_tools/hyperparameters_ml.py
machine_learning_tools/machine_learning_utils.py
machine_learning_tools/matplotlib_ml.py
machine_learning_tools/numpy_ml.py
machine_learning_tools/pandas_ml.py
machine_learning_tools/preprocessing_ml.py
machine_learning_tools/seaborn_ml.py
machine_learning_tools/sklearn_models.py
machine_learning_tools/sklearn_utils.py
machine_learning_tools/statsmodels_utils.py
machine_learning_tools/visualizations_ml.py
machine_learning_tools-1.0.0.dist-info/DESCRIPTION.rst
machine_learning_tools-1.0.0.dist-info/METADATA
machine_learning_tools-1.0.0.dist-info/RECORD
machine_learning_tools-1.0.0.dist-info/WHEEL
machine_learning_tools-1.0.0.dist-info/metadata.json
machine_learning_tools-1.0.0.dist-info/top_level.txt
